honey_nudger/__init__.py
honey_nudger-0.0.1.dist-info/LICENSE
honey_nudger-0.0.1.dist-info/METADATA
honey_nudger-0.0.1.dist-info/NOTICE
honey_nudger-0.0.1.dist-info/WHEEL
honey_nudger-0.0.1.dist-info/top_level.txt
honey_nudger-0.0.1.dist-info/RECORD
