Metadata-Version: 2.1
Name: honey-nudger
Version: 0.0.1
Summary: Reserving package name for the upcoming Honey Nudger OSS project.
Home-page: https://github.com/honeynudger/honey-nudger-oss
Author: Daniel Carpenter
Author-email: dan@honeynudger.ai
Classifier: Programming Language :: Python :: 3
Classifier: License :: OSI Approved :: Apache Software License
Classifier: Operating System :: OS Independent
Requires-Python: >=3.6
License-File: LICENSE
License-File: NOTICE
